filecollector/__init__.py
filecollector/collector.py
filecollector/server.py
filecollector-0.2.1.data/scripts/filecollector
filecollector-0.2.1.dist-info/LICENSE
filecollector-0.2.1.dist-info/METADATA
filecollector-0.2.1.dist-info/WHEEL
filecollector-0.2.1.dist-info/top_level.txt
filecollector-0.2.1.dist-info/RECORD
