Metadata-Version: 2.1
Name: filecollector
Version: 0.2.1
Summary: Simple file collector - compress/serve/send/anonymizie files
Home-page: https://github.com/oleewere/filecollector
Author: Oliver Szabo
Author-email: oleewere@gmail.com
License: Apache 2.0
Platform: UNKNOWN
Classifier: Programming Language :: Python
Classifier: Programming Language :: Python :: 3
Classifier: Operating System :: OS Independent
Requires-Python: >=3.5
Requires-Dist: PyYAML (>=5.3.1)
Requires-Dist: pid (>=3.0.3)
Requires-Dist: fluent-logger (>=0.9.6)
